{
  "meta": {
    "normalized_at": "2026-01-01T22:40:24Z",
    "version": 1,
    "input_relpath": "environmental/ecoregions/antarctica_the_frozen_frontier.json",
    "source_kind": "original_input"
  },
  "poster": {
    "poster_id": "environmental__ecoregions_mosaic__antarctica__antarctica_the_frozen_frontier",
    "derived_id": "environmental__ecoregions_mosaic__antarctica__antarctica_the_frozen_frontier",
    "continent": "antarctica",
    "domain": "environmental",
    "poster_family": "ecoregions_mosaic",
    "filename": "antarctica_the_frozen_frontier.json"
  },
  "tags": {
    "continent": [
      "antarctica"
    ],
    "domain": [
      "environmental"
    ],
    "poster_family": [
      "ecoregions_mosaic"
    ],
    "flat": [
      "continent:antarctica",
      "domain:environmental",
      "poster_family:ecoregions_mosaic"
    ]
  },
  "layout": {},
  "content": {
    "blocks": [],
    "notes": "Content not refactored in Phase 1; original preserved under payload."
  },
  "assets": [],
  "sources": [
    {
      "kind": "original_input",
      "path": "environmental/ecoregions/antarctica_the_frozen_frontier.json"
    }
  ],
  "qa": {
    "status": "pass",
    "warnings": [],
    "errors": []
  },
  "payload": {
    "continent": "Antarctica",
    "poster_title": "The Frozen Frontier",
    "items": [
      {
        "entry_number": "1",
        "ecoregion_name": "Antarctic Plateau & Coast",
        "image_url": null,
        "description": "A continent of ice and wind—vast plateaus, coastal cliffs, and penguin shores show Earth at its rawest."
      }
    ]
  }
}
